pantsbuild.pants.contrib.codeanalysis-1.29.0-py3.6-nspkg.pth
pants/contrib/codeanalysis/__init__.py
pants/contrib/codeanalysis/register.py
pants/contrib/codeanalysis/tasks/__init__.py
pants/contrib/codeanalysis/tasks/bundle_entries.py
pants/contrib/codeanalysis/tasks/extract_java.py
pants/contrib/codeanalysis/tasks/index_java.py
pants/contrib/codeanalysis/tasks/indexable_java_targets.py
pantsbuild.pants.contrib.codeanalysis-1.29.0.dist-info/METADATA
pantsbuild.pants.contrib.codeanalysis-1.29.0.dist-info/RECORD
pantsbuild.pants.contrib.codeanalysis-1.29.0.dist-info/WHEEL
pantsbuild.pants.contrib.codeanalysis-1.29.0.dist-info/entry_points.txt
pantsbuild.pants.contrib.codeanalysis-1.29.0.dist-info/namespace_packages.txt
pantsbuild.pants.contrib.codeanalysis-1.29.0.dist-info/top_level.txt
pantsbuild.pants.contrib.codeanalysis-1.29.0.dist-info/zip-safe
